[
  {
    "_id": "690901b5f2ca4f4f65333364",
    "name": "Coupon 1",
    "description": "Coupon 1 description",
    "code": "CODE1000",
    "discount_type": "percentage",
    "discount_value": 12,
    "usage_limit_per_user": 3,
    "total_usage_limit": 354,
    "expiration_date": "2026-01-02T19:25:41.045Z",
    "minimum_purchase_amount": 1160,
    "is_active": true,
    "__v": 0,
    "createdAt": "2025-11-03T19:25:41.064Z",
    "updatedAt": "2025-11-03T19:25:41.064Z"
  },
  {
    "_id": "690901b5f2ca4f4f65333365",
    "name": "Coupon 2",
    "description": "Coupon 2 description",
    "code": "CODE1001",
    "discount_type": "fixed_amount",
    "discount_value": 397,
    "usage_limit_per_user": 5,
    "total_usage_limit": 217,
    "expiration_date": "2026-01-03T19:25:41.045Z",
    "minimum_purchase_amount": 2222,
    "is_active": true,
    "__v": 0,
    "createdAt": "2025-11-03T19:25:41.064Z",
    "updatedAt": "2025-11-03T19:25:41.064Z"
  },
  {
    "_id": "690901b5f2ca4f4f65333366",
    "name": "Coupon 3",
    "description": "Coupon 3 description",
    "code": "CODE1002",
    "discount_type": "percentage",
    "discount_value": 10,
    "usage_limit_per_user": 1,
    "total_usage_limit": 607,
    "expiration_date": "2026-01-04T19:25:41.045Z",
    "minimum_purchase_amount": 1809,
    "is_active": true,
    "__v": 0,
    "createdAt": "2025-11-03T19:25:41.064Z",
    "updatedAt": "2025-11-03T19:25:41.064Z"
  },
  {
    "_id": "690901b5f2ca4f4f65333367",
    "name": "Coupon 4",
    "description": "Coupon 4 description",
    "code": "CODE1003",
    "discount_type": "fixed_amount",
    "discount_value": 912,
    "usage_limit_per_user": 5,
    "total_usage_limit": 941,
    "expiration_date": "2026-01-05T19:25:41.045Z",
    "minimum_purchase_amount": 664,
    "is_active": true,
    "__v": 0,
    "createdAt": "2025-11-03T19:25:41.064Z",
    "updatedAt": "2025-11-03T19:25:41.064Z"
  },
  {
    "_id": "690901b5f2ca4f4f65333368",
    "name": "Coupon 5",
    "description": "Coupon 5 description",
    "code": "CODE1004",
    "discount_type": "percentage",
    "discount_value": 27,
    "usage_limit_per_user": 2,
    "total_usage_limit": 43,
    "expiration_date": "2026-01-06T19:25:41.045Z",
    "minimum_purchase_amount": 1926,
    "is_active": true,
    "__v": 0,
    "createdAt": "2025-11-03T19:25:41.064Z",
    "updatedAt": "2025-11-03T19:25:41.064Z"
  },
  {
    "_id": "690901b5f2ca4f4f65333369",
    "name": "Coupon 6",
    "description": "Coupon 6 description",
    "code": "CODE1005",
    "discount_type": "fixed_amount",
    "discount_value": 727,
    "usage_limit_per_user": 4,
    "total_usage_limit": 772,
    "expiration_date": "2026-01-07T19:25:41.045Z",
    "minimum_purchase_amount": 792,
    "is_active": true,
    "__v": 0,
    "createdAt": "2025-11-03T19:25:41.064Z",
    "updatedAt": "2025-11-03T19:25:41.064Z"
  },
  {
    "_id": "690901b5f2ca4f4f6533336a",
    "name": "Coupon 7",
    "description": "Coupon 7 description",
    "code": "CODE1006",
    "discount_type": "percentage",
    "discount_value": 7,
    "usage_limit_per_user": 1,
    "total_usage_limit": 938,
    "expiration_date": "2026-01-08T19:25:41.045Z",
    "minimum_purchase_amount": 103,
    "is_active": true,
    "__v": 0,
    "createdAt": "2025-11-03T19:25:41.065Z",
    "updatedAt": "2025-11-03T19:25:41.065Z"
  },
  {
    "_id": "690901b5f2ca4f4f6533336b",
    "name": "Coupon 8",
    "description": "Coupon 8 description",
    "code": "CODE1007",
    "discount_type": "fixed_amount",
    "discount_value": 181,
    "usage_limit_per_user": 5,
    "total_usage_limit": 983,
    "expiration_date": "2026-01-09T19:25:41.045Z",
    "minimum_purchase_amount": 1283,
    "is_active": true,
    "__v": 0,
    "createdAt": "2025-11-03T19:25:41.065Z",
    "updatedAt": "2025-11-03T19:25:41.065Z"
  },
  {
    "_id": "690901b5f2ca4f4f6533336c",
    "name": "Coupon 9",
    "description": "Coupon 9 description",
    "code": "CODE1008",
    "discount_type": "percentage",
    "discount_value": 8,
    "usage_limit_per_user": 1,
    "total_usage_limit": 647,
    "expiration_date": "2026-01-10T19:25:41.045Z",
    "minimum_purchase_amount": 2694,
    "is_active": true,
    "__v": 0,
    "createdAt": "2025-11-03T19:25:41.065Z",
    "updatedAt": "2025-11-03T19:25:41.065Z"
  },
  {
    "_id": "690901b5f2ca4f4f6533336d",
    "name": "Coupon 10",
    "description": "Coupon 10 description",
    "code": "CODE1009",
    "discount_type": "fixed_amount",
    "discount_value": 589,
    "usage_limit_per_user": 5,
    "total_usage_limit": 472,
    "expiration_date": "2026-01-11T19:25:41.045Z",
    "minimum_purchase_amount": 157,
    "is_active": true,
    "__v": 0,
    "createdAt": "2025-11-03T19:25:41.065Z",
    "updatedAt": "2025-11-03T19:25:41.065Z"
  },
  {
    "_id": "690901b5f2ca4f4f6533336e",
    "name": "Coupon 11",
    "description": "Coupon 11 description",
    "code": "CODE1010",
    "discount_type": "percentage",
    "discount_value": 24,
    "usage_limit_per_user": 4,
    "total_usage_limit": 403,
    "expiration_date": "2026-01-12T19:25:41.045Z",
    "minimum_purchase_amount": 430,
    "is_active": true,
    "__v": 0,
    "createdAt": "2025-11-03T19:25:41.065Z",
    "updatedAt": "2025-11-03T19:25:41.065Z"
  },
  {
    "_id": "690901b5f2ca4f4f6533336f",
    "name": "Coupon 12",
    "description": "Coupon 12 description",
    "code": "CODE1011",
    "discount_type": "fixed_amount",
    "discount_value": 398,
    "usage_limit_per_user": 1,
    "total_usage_limit": 433,
    "expiration_date": "2026-01-13T19:25:41.045Z",
    "minimum_purchase_amount": 2210,
    "is_active": true,
    "__v": 0,
    "createdAt": "2025-11-03T19:25:41.065Z",
    "updatedAt": "2025-11-03T19:25:41.065Z"
  },
  {
    "_id": "690901b5f2ca4f4f65333370",
    "name": "Coupon 13",
    "description": "Coupon 13 description",
    "code": "CODE1012",
    "discount_type": "percentage",
    "discount_value": 13,
    "usage_limit_per_user": 4,
    "total_usage_limit": 587,
    "expiration_date": "2026-01-14T19:25:41.045Z",
    "minimum_purchase_amount": 981,
    "is_active": true,
    "__v": 0,
    "createdAt": "2025-11-03T19:25:41.065Z",
    "updatedAt": "2025-11-03T19:25:41.065Z"
  },
  {
    "_id": "690901b5f2ca4f4f65333371",
    "name": "Coupon 14",
    "description": "Coupon 14 description",
    "code": "CODE1013",
    "discount_type": "fixed_amount",
    "discount_value": 389,
    "usage_limit_per_user": 5,
    "total_usage_limit": 955,
    "expiration_date": "2026-01-15T19:25:41.045Z",
    "minimum_purchase_amount": 2796,
    "is_active": true,
    "__v": 0,
    "createdAt": "2025-11-03T19:25:41.065Z",
    "updatedAt": "2025-11-03T19:25:41.065Z"
  },
  {
    "_id": "690901b5f2ca4f4f65333372",
    "name": "Coupon 15",
    "description": "Coupon 15 description",
    "code": "CODE1014",
    "discount_type": "percentage",
    "discount_value": 8,
    "usage_limit_per_user": 5,
    "total_usage_limit": 544,
    "expiration_date": "2026-01-16T19:25:41.045Z",
    "minimum_purchase_amount": 1844,
    "is_active": true,
    "__v": 0,
    "createdAt": "2025-11-03T19:25:41.065Z",
    "updatedAt": "2025-11-03T19:25:41.065Z"
  },
  {
    "_id": "690901b5f2ca4f4f65333373",
    "name": "Coupon 16",
    "description": "Coupon 16 description",
    "code": "CODE1015",
    "discount_type": "fixed_amount",
    "discount_value": 299,
    "usage_limit_per_user": 3,
    "total_usage_limit": 621,
    "expiration_date": "2026-01-17T19:25:41.045Z",
    "minimum_purchase_amount": 564,
    "is_active": true,
    "__v": 0,
    "createdAt": "2025-11-03T19:25:41.066Z",
    "updatedAt": "2025-11-03T19:25:41.066Z"
  },
  {
    "_id": "690901b5f2ca4f4f65333374",
    "name": "Coupon 17",
    "description": "Coupon 17 description",
    "code": "CODE1016",
    "discount_type": "percentage",
    "discount_value": 12,
    "usage_limit_per_user": 4,
    "total_usage_limit": 779,
    "expiration_date": "2026-01-18T19:25:41.045Z",
    "minimum_purchase_amount": 254,
    "is_active": true,
    "__v": 0,
    "createdAt": "2025-11-03T19:25:41.066Z",
    "updatedAt": "2025-11-03T19:25:41.066Z"
  },
  {
    "_id": "690901b5f2ca4f4f65333375",
    "name": "Coupon 18",
    "description": "Coupon 18 description",
    "code": "CODE1017",
    "discount_type": "fixed_amount",
    "discount_value": 428,
    "usage_limit_per_user": 4,
    "total_usage_limit": 294,
    "expiration_date": "2026-01-19T19:25:41.045Z",
    "minimum_purchase_amount": 2933,
    "is_active": true,
    "__v": 0,
    "createdAt": "2025-11-03T19:25:41.066Z",
    "updatedAt": "2025-11-03T19:25:41.066Z"
  },
  {
    "_id": "690901b5f2ca4f4f65333376",
    "name": "Coupon 19",
    "description": "Coupon 19 description",
    "code": "CODE1018",
    "discount_type": "percentage",
    "discount_value": 11,
    "usage_limit_per_user": 5,
    "total_usage_limit": 818,
    "expiration_date": "2026-01-20T19:25:41.045Z",
    "minimum_purchase_amount": 2697,
    "is_active": true,
    "__v": 0,
    "createdAt": "2025-11-03T19:25:41.066Z",
    "updatedAt": "2025-11-03T19:25:41.066Z"
  },
  {
    "_id": "690901b5f2ca4f4f65333377",
    "name": "Coupon 20",
    "description": "Coupon 20 description",
    "code": "CODE1019",
    "discount_type": "fixed_amount",
    "discount_value": 520,
    "usage_limit_per_user": 4,
    "total_usage_limit": 381,
    "expiration_date": "2026-01-21T19:25:41.045Z",
    "minimum_purchase_amount": 2576,
    "is_active": true,
    "__v": 0,
    "createdAt": "2025-11-03T19:25:41.066Z",
    "updatedAt": "2025-11-03T19:25:41.066Z"
  }
]
